{"version": 0.6, "generator": "Overpass API 0.7.62.7 375dc00a", "osm3s": {"timestamp_osm_base": "2025-07-06T21:55:15Z", "copyright": "The data included in this document is from www.openstreetmap.org. The data is made available under ODbL."}, "elements": [{"type": "node", "id": 21934734, "lat": 54.9168663, "lon": 9.7786727}, {"type": "node", "id": 21934735, "lat": 54.9167127, "lon": 9.7786307}, {"type": "node", "id": 21934736, "lat": 54.9159173, "lon": 9.7811389}, {"type": "node", "id": 21934737, "lat": 54.9155955, "lon": 9.78168}, {"type": "node", "id": 21934738, "lat": 54.9155155, "lon": 9.7815027}, {"type": "node", "id": 21934749, "lat": 54.9121751, "lon": 9.7842559}, {"type": "node", "id": 21934750, "lat": 54.9121978, "lon": 9.7844585}, {"type": "node", "id": 21934755, "lat": 54.907719, "lon": 9.7846956}, {"type": "node", "id": 256035076, "lat": 54.8974604, "lon": 9.8156257}, {"type": "node", "id": 256451898, "lat": 54.8947889, "lon": 9.8092997}, {"type": "node", "id": 256451899, "lat": 54.8947434, "lon": 9.8133284}, {"type": "node", "id": 256451905, "lat": 54.9210983, "lon": 9.8328124}, {"type": "node", "id": 256451906, "lat": 54.9294743, "lon": 9.8336128}, {"type": "node", "id": 256451907, "lat": 54.9308138, "lon": 9.8219287}, {"type": "node", "id": 256451908, "lat": 54.932836, "lon": 9.8168629}, {"type": "node", "id": 256451909, "lat": 54.9326209, "lon": 9.811421}, {"type": "node", "id": 256451912, "lat": 54.9215926, "lon": 9.7715193}, {"type": "node", "id": 256451913, "lat": 54.9178464, "lon": 9.7731268}, {"type": "node", "id": 256451915, "lat": 54.9112609, "lon": 9.7850333}, {"type": "node", "id": 256451916, "lat": 54.9086103, "lon": 9.7853127}, {"type": "node", "id": 256451917, "lat": 54.9029797, "lon": 9.7914486}, {"type": "node", "id": 256451918, "lat": 54.9008436, "lon": 9.8005392}, {"type": "node", "id": 256451922, "lat": 54.8953072, "lon": 9.8070306}, {"type": "node", "id": 256454705, "lat": 54.8972482, "lon": 9.815302}, {"type": "node", "id": 256454707, "lat": 54.9190595, "lon": 9.8319281}, {"type": "node", "id": 257934609, "lat": 54.903579, "lon": 9.792034}, {"type": "node", "id": 257949722, "lat": 54.923038, "lon": 9.7824406}, {"type": "node", "id": 257950063, "lat": 54.9260231, "lon": 9.8105728}, {"type": "node", "id": 257950064, "lat": 54.9250414, "lon": 9.8083005}, {"type": "node", "id": 257950065, "lat": 54.9252031, "lon": 9.8185459}, {"type": "node", "id": 257950067, "lat": 54.9214669, "lon": 9.8059574}, {"type": "node", "id": 257950068, "lat": 54.9246003, "lon": 9.8030394}, {"type": "node", "id": 257950069, "lat": 54.9232038, "lon": 9.7942203}, {"type": "node", "id": 257950070, "lat": 54.9231236, "lon": 9.7886065}, {"type": "node", "id": 257950071, "lat": 54.9229094, "lon": 9.7868684}, {"type": "node", "id": 257950072, "lat": 54.9226551, "lon": 9.785774}, {"type": "node", "id": 257950073, "lat": 54.9221587, "lon": 9.7838053}, {"type": "node", "id": 257950074, "lat": 54.9219953, "lon": 9.7828612}, {"type": "node", "id": 259817079, "lat": 54.9230265, "lon": 9.7875148}, {"type": "node", "id": 262655606, "lat": 54.9099317, "lon": 9.7854348}, {"type": "node", "id": 265606997, "lat": 54.896882, "lon": 9.8036}, {"type": "node", "id": 267255312, "lat": 54.930338, "lon": 9.829879}, {"type": "node", "id": 267255313, "lat": 54.9305794, "lon": 9.8270747}, {"type": "node", "id": 269429615, "lat": 54.9308571, "lon": 9.8112833}, {"type": "node", "id": 269429616, "lat": 54.9262626, "lon": 9.8117696}, {"type": "node", "id": 269429683, "lat": 54.9325924, "lon": 9.8193299}, {"type": "node", "id": 269559183, "lat": 54.9247841, "lon": 9.8029321}, {"type": "node", "id": 269559184, "lat": 54.9246604, "lon": 9.8022455}, {"type": "node", "id": 269559185, "lat": 54.9246866, "lon": 9.8018754}, {"type": "node", "id": 269559186, "lat": 54.9244122, "lon": 9.8015857}, {"type": "node", "id": 269559187, "lat": 54.9239652, "lon": 9.8012504}, {"type": "node", "id": 269559188, "lat": 54.9232408, "lon": 9.8011163}, {"type": "node", "id": 269561273, "lat": 54.9241304, "lon": 9.8083237}, {"type": "node", "id": 269561274, "lat": 54.9243449, "lon": 9.8106924}, {"type": "node", "id": 269561275, "lat": 54.9216563, "lon": 9.8195042}, {"type": "node", "id": 269561276, "lat": 54.9218142, "lon": 9.8213838}, {"type": "node", "id": 269561277, "lat": 54.9195946, "lon": 9.8240724}, {"type": "node", "id": 269561278, "lat": 54.917427, "lon": 9.8181745}, {"type": "node", "id": 269561279, "lat": 54.9166677, "lon": 9.8090476}, {"type": "node", "id": 269561280, "lat": 54.91913, "lon": 9.807225}, {"type": "node", "id": 269561281, "lat": 54.9232439, "lon": 9.803313}, {"type": "node", "id": 269562082, "lat": 54.922392, "lon": 9.8240418}, {"type": "node", "id": 269562083, "lat": 54.9215791, "lon": 9.8245133}, {"type": "node", "id": 269562084, "lat": 54.9192935, "lon": 9.8086122}, {"type": "node", "id": 269562146, "lat": 54.9188838, "lon": 9.8240835}, {"type": "node", "id": 269562344, "lat": 54.915957, "lon": 9.8108346}, {"type": "node", "id": 269562594, "lat": 54.9290889, "lon": 9.8141192}, {"type": "node", "id": 269562595, "lat": 54.9286296, "lon": 9.8149839}, {"type": "node", "id": 269563659, "lat": 54.9185855, "lon": 9.8083422}, {"type": "node", "id": 271880493, "lat": 54.9183234, "lon": 9.8223661}, {"type": "node", "id": 272803819, "lat": 54.9116025, "lon": 9.8261422}, {"type": "node", "id": 272803820, "lat": 54.9148426, "lon": 9.8285495}, {"type": "node", "id": 272803821, "lat": 54.9178509, "lon": 9.8310269}, {"type": "node", "id": 272803822, "lat": 54.9200323, "lon": 9.8324377}, {"type": "node", "id": 272803823, "lat": 54.9228725, "lon": 9.8329881}, {"type": "node", "id": 272809341, "lat": 54.9180174, "lon": 9.8210129}, {"type": "node", "id": 272809342, "lat": 54.91755, "lon": 9.8187571}, {"type": "node", "id": 273496463, "lat": 54.9034753, "lon": 9.7901924}, {"type": "node", "id": 274345472, "lat": 54.901796, "lon": 9.8242382}, {"type": "node", "id": 275362528, "lat": 54.9222325, "lon": 9.8192534}, {"type": "node", "id": 276805096, "lat": 54.9018612, "lon": 9.7959248}, {"type": "node", "id": 276805097, "lat": 54.902224, "lon": 9.7964764}, {"type": "node", "id": 277194515, "lat": 54.901116, "lon": 9.7967144}, {"type": "node", "id": 280836130, "lat": 54.9217057, "lon": 9.8203453}, {"type": "node", "id": 292676977, "lat": 54.924682, "lon": 9.8025164}, {"type": "node", "id": 388341503, "lat": 54.9210386, "lon": 9.8245776}, {"type": "node", "id": 404456556, "lat": 54.9026761, "lon": 9.7950901}, {"type": "node", "id": 404456560, "lat": 54.9031389, "lon": 9.7932276}, {"type": "node", "id": 404456565, "lat": 54.9024058, "lon": 9.7960387}, {"type": "node", "id": 1308214440, "lat": 54.9095609, "lon": 9.7854428}, {"type": "node", "id": 1403182045, "lat": 54.8953049, "lon": 9.8129247}, {"type": "node", "id": 1403182046, "lat": 54.8957056, "lon": 9.8163146}, {"type": "node", "id": 1403182047, "lat": 54.8960429, "lon": 9.8133337}, {"type": "node", "id": 1403182048, "lat": 54.8946054, "lon": 9.8104799}, {"type": "node", "id": 1403182049, "lat": 54.8967093, "lon": 9.8129931}, {"type": "node", "id": 1403182050, "lat": 54.8955771, "lon": 9.8130172}, {"type": "node", "id": 1403182051, "lat": 54.8959085, "lon": 9.8164752}, {"type": "node", "id": 1403182052, "lat": 54.894772, "lon": 9.8131621}, {"type": "node", "id": 1403182053, "lat": 54.8962512, "lon": 9.8134008}, {"type": "node", "id": 1403182054, "lat": 54.8950134, "lon": 9.8129784}, {"type": "node", "id": 1403182055, "lat": 54.8944156, "lon": 9.8122863}, {"type": "node", "id": 1403182056, "lat": 54.8967363, "lon": 9.8132318}, {"type": "node", "id": 1444782746, "lat": 54.9005158, "lon": 9.7968648}, {"type": "node", "id": 1444782747, "lat": 54.9006423, "lon": 9.7966663}, {"type": "node", "id": 1444782750, "lat": 54.9007847, "lon": 9.7969303}, {"type": "node", "id": 1444782756, "lat": 54.9005467, "lon": 9.8000244}, {"type": "node", "id": 1444782758, "lat": 54.9005096, "lon": 9.7997884}, {"type": "node", "id": 1444782769, "lat": 54.9008428, "lon": 9.7991822}, {"type": "node", "id": 1445236122, "lat": 54.9011104, "lon": 9.7986439}, {"type": "node", "id": 1503903654, "lat": 54.9076669, "lon": 9.7846618}, {"type": "node", "id": 1503903688, "lat": 54.9076036, "lon": 9.7847758}, {"type": "node", "id": 1503903705, "lat": 54.9075957, "lon": 9.7856037}, {"type": "node", "id": 1503903712, "lat": 54.9075951, "lon": 9.7849853}, {"type": "node", "id": 1665776783, "lat": 54.9076496, "lon": 9.7846618}, {"type": "node", "id": 1905360290, "lat": 54.9017365, "lon": 9.8242299}, {"type": "node", "id": 1914283146, "lat": 54.9162799, "lon": 9.8105042}, {"type": "node", "id": 1914283149, "lat": 54.9163652, "lon": 9.8101963}, {"type": "node", "id": 1914283151, "lat": 54.9163055, "lon": 9.8098361}, {"type": "node", "id": 1914283159, "lat": 54.9167548, "lon": 9.8096585}, {"type": "node", "id": 1914283182, "lat": 54.9187258, "lon": 9.8088893}, {"type": "node", "id": 2091032556, "lat": 54.9276343, "lon": 9.8315954}, {"type": "node", "id": 2091032618, "lat": 54.9274247, "lon": 9.8337731}, {"type": "node", "id": 2122433047, "lat": 54.9141536, "lon": 9.7826681}, {"type": "node", "id": 2122433048, "lat": 54.914134, "lon": 9.782597}, {"type": "node", "id": 2228740422, "lat": 54.9177006, "lon": 9.7735526}, {"type": "node", "id": 2228740433, "lat": 54.910716, "lon": 9.7854121}, {"type": "node", "id": 2381789930, "lat": 54.9192301, "lon": 9.8240503}, {"type": "node", "id": 2381789948, "lat": 54.9200708, "lon": 9.8241769}, {"type": "node", "id": 2381790353, "lat": 54.9327366, "lon": 9.8132889}, {"type": "node", "id": 2425024840, "lat": 54.9006286, "lon": 9.7971243}, {"type": "node", "id": 2425024841, "lat": 54.9007756, "lon": 9.7974806}, {"type": "node", "id": 2425024848, "lat": 54.9010178, "lon": 9.7980441}, {"type": "node", "id": 2425024869, "lat": 54.9012075, "lon": 9.7984756}, {"type": "node", "id": 2434261097, "lat": 54.9304727, "lon": 9.8283135}, {"type": "node", "id": 2482546960, "lat": 54.8982887, "lon": 9.8034659}, {"type": "node", "id": 2527175660, "lat": 54.9316042, "lon": 9.8215749}, {"type": "node", "id": 2835727905, "lat": 54.9184261, "lon": 9.7726359}, {"type": "node", "id": 2835727908, "lat": 54.9184816, "lon": 9.7728291}, {"type": "node", "id": 2835727909, "lat": 54.918914, "lon": 9.7729768}, {"type": "node", "id": 2835727910, "lat": 54.9195807, "lon": 9.7724309}, {"type": "node", "id": 2835727911, "lat": 54.9206289, "lon": 9.7721156}, {"type": "node", "id": 2835727912, "lat": 54.9208768, "lon": 9.7722374}, {"type": "node", "id": 2835727913, "lat": 54.9210166, "lon": 9.7714598}, {"type": "node", "id": 2835727914, "lat": 54.921366, "lon": 9.7713705}, {"type": "node", "id": 2835727917, "lat": 54.9217488, "lon": 9.7720223}, {"type": "node", "id": 2835727918, "lat": 54.9220635, "lon": 9.7750374}, {"type": "node", "id": 2835727919, "lat": 54.9212531, "lon": 9.7756345}, {"type": "node", "id": 2835727924, "lat": 54.9217933, "lon": 9.7783221}, {"type": "node", "id": 2835727955, "lat": 54.9230789, "lon": 9.7778446}, {"type": "node", "id": 2985121738, "lat": 54.9168821, "lon": 9.7786775}, {"type": "node", "id": 2985121740, "lat": 54.9171591, "lon": 9.7766364}, {"type": "node", "id": 2986159056, "lat": 54.9154573, "lon": 9.7815603}, {"type": "node", "id": 3098817463, "lat": 54.9269352, "lon": 9.8336004}, {"type": "node", "id": 3098817468, "lat": 54.9269562, "lon": 9.8352975}, {"type": "node", "id": 3098817472, "lat": 54.9266906, "lon": 9.836553}, {"type": "node", "id": 3098817501, "lat": 54.9252799, "lon": 9.8350447}, {"type": "node", "id": 3098817511, "lat": 54.9262386, "lon": 9.8368418}, {"type": "node", "id": 3098817523, "lat": 54.9266597, "lon": 9.8361963}, {"type": "node", "id": 3098817538, "lat": 54.926824, "lon": 9.8361533}, {"type": "node", "id": 3098817574, "lat": 54.9267802, "lon": 9.8353126}, {"type": "node", "id": 3138120194, "lat": 54.9231798, "lon": 9.830064}, {"type": "node", "id": 3556970984, "lat": 54.915628, "lon": 9.7815828}, {"type": "node", "id": 3556971520, "lat": 54.9174732, "lon": 9.7748467}, {"type": "node", "id": 3887612399, "lat": 54.9213391, "lon": 9.8245761}, {"type": "node", "id": 3898278428, "lat": 54.9106551, "lon": 9.785395}, {"type": "node", "id": 3898278430, "lat": 54.9110888, "lon": 9.7851509}, {"type": "node", "id": 4377022445, "lat": 54.9291166, "lon": 9.8140688}, {"type": "node", "id": 4377022446, "lat": 54.9294539, "lon": 9.8172364}, {"type": "node", "id": 4377022447, "lat": 54.9301532, "lon": 9.812406}, {"type": "node", "id": 4377022448, "lat": 54.9304733, "lon": 9.8122921}, {"type": "node", "id": 4377022449, "lat": 54.930679, "lon": 9.8141916}, {"type": "node", "id": 4377022450, "lat": 54.9307887, "lon": 9.8164231}, {"type": "node", "id": 4377811853, "lat": 54.9255053, "lon": 9.8095277}, {"type": "node", "id": 4377811881, "lat": 54.9266995, "lon": 9.8127102}, {"type": "node", "id": 4377812097, "lat": 54.9277518, "lon": 9.8137738}, {"type": "node", "id": 4456183895, "lat": 54.9194171, "lon": 9.8068426}, {"type": "node", "id": 4456183896, "lat": 54.9194525, "lon": 9.807041}, {"type": "node", "id": 4456183901, "lat": 54.9196298, "lon": 9.806695}, {"type": "node", "id": 4456183915, "lat": 54.9202279, "lon": 9.8064711}, {"type": "node", "id": 4491328926, "lat": 54.9190527, "lon": 9.7729124}, {"type": "node", "id": 4491328927, "lat": 54.9193433, "lon": 9.7725838}, {"type": "node", "id": 4491328928, "lat": 54.9216958, "lon": 9.7717446}, {"type": "node", "id": 4491328929, "lat": 54.9225355, "lon": 9.7826096}, {"type": "node", "id": 4491328930, "lat": 54.9232423, "lon": 9.779969}, {"type": "node", "id": 4491328931, "lat": 54.9181825, "lon": 9.773328}, {"type": "node", "id": 4582325784, "lat": 54.9237085, "lon": 9.8304608}, {"type": "node", "id": 4582325785, "lat": 54.9240907, "lon": 9.8319039}, {"type": "node", "id": 4582325786, "lat": 54.924409, "lon": 9.8328158}, {"type": "node", "id": 4582325787, "lat": 54.9248329, "lon": 9.8340523}, {"type": "node", "id": 4582325788, "lat": 54.9261615, "lon": 9.835785}, {"type": "node", "id": 4582325889, "lat": 54.9259056, "lon": 9.8354015}, {"type": "node", "id": 4582325890, "lat": 54.9256159, "lon": 9.8348114}, {"type": "node", "id": 4582326019, "lat": 54.9151473, "lon": 9.8216526}, {"type": "node", "id": 4582326020, "lat": 54.9153493, "lon": 9.8193271}, {"type": "node", "id": 4582326021, "lat": 54.9149145, "lon": 9.8194344}, {"type": "node", "id": 4582326022, "lat": 54.9146185, "lon": 9.819716}, {"type": "node", "id": 4582326023, "lat": 54.9140542, "lon": 9.8204456}, {"type": "node", "id": 4582326024, "lat": 54.9135765, "lon": 9.821137}, {"type": "node", "id": 4582326025, "lat": 54.9135715, "lon": 9.8212456}, {"type": "node", "id": 4582326026, "lat": 54.9134502, "lon": 9.8215477}, {"type": "node", "id": 4582326027, "lat": 54.9135195, "lon": 9.8209668}, {"type": "node", "id": 4582326028, "lat": 54.9133747, "lon": 9.8205059}, {"type": "node", "id": 4582326029, "lat": 54.9136661, "lon": 9.820227}, {"type": "node", "id": 4582326030, "lat": 54.9138958, "lon": 9.8207312}, {"type": "node", "id": 4582326031, "lat": 54.9149658, "lon": 9.8216646}, {"type": "node", "id": 4582326032, "lat": 54.9143013, "lon": 9.8216861}, {"type": "node", "id": 4582326033, "lat": 54.9143182, "lon": 9.8222145}, {"type": "node", "id": 4582326034, "lat": 54.9144879, "lon": 9.8235529}, {"type": "node", "id": 4582326035, "lat": 54.914309, "lon": 9.8236629}, {"type": "node", "id": 4582326036, "lat": 54.9141456, "lon": 9.8255028}, {"type": "node", "id": 4582326037, "lat": 54.9149843, "lon": 9.8257737}, {"type": "node", "id": 4582326038, "lat": 54.9154545, "lon": 9.8257362}, {"type": "node", "id": 4582326039, "lat": 54.9153389, "lon": 9.8269486}, {"type": "node", "id": 4582326040, "lat": 54.9148841, "lon": 9.8266857}, {"type": "node", "id": 4582326041, "lat": 54.9130918, "lon": 9.8233142}, {"type": "node", "id": 4582326042, "lat": 54.913377, "lon": 9.8215359}, {"type": "node", "id": 4582326043, "lat": 54.9056504, "lon": 9.823421}, {"type": "node", "id": 4582326044, "lat": 54.9038438, "lon": 9.8254139}, {"type": "node", "id": 4582326045, "lat": 54.904032, "lon": 9.8255078}, {"type": "node", "id": 4582326046, "lat": 54.9041646, "lon": 9.8255104}, {"type": "node", "id": 4582326047, "lat": 54.904692, "lon": 9.8252824}, {"type": "node", "id": 4582326048, "lat": 54.9037652, "lon": 9.8258162}, {"type": "node", "id": 4582326049, "lat": 54.9033689, "lon": 9.8260201}, {"type": "node", "id": 4582326050, "lat": 54.9032995, "lon": 9.8263446}, {"type": "node", "id": 4582326051, "lat": 54.9029509, "lon": 9.8264465}, {"type": "node", "id": 4582326052, "lat": 54.9024109, "lon": 9.8242845}, {"type": "node", "id": 4582326053, "lat": 54.9018693, "lon": 9.8242468}, {"type": "node", "id": 4582326054, "lat": 54.9015298, "lon": 9.8242069}, {"type": "node", "id": 4582326055, "lat": 54.9007355, "lon": 9.8240245}, {"type": "node", "id": 4582326056, "lat": 54.9004857, "lon": 9.8238931}, {"type": "node", "id": 4582326057, "lat": 54.9001325, "lon": 9.8235417}, {"type": "node", "id": 4582326058, "lat": 54.8998965, "lon": 9.8231742}, {"type": "node", "id": 4582326059, "lat": 54.8997053, "lon": 9.8227397}, {"type": "node", "id": 4582326060, "lat": 54.8995788, "lon": 9.8223079}, {"type": "node", "id": 4582326061, "lat": 54.8994061, "lon": 9.8222998}, {"type": "node", "id": 4582326062, "lat": 54.8978344, "lon": 9.8224098}, {"type": "node", "id": 4582326063, "lat": 54.8975753, "lon": 9.8223588}, {"type": "node", "id": 4582326064, "lat": 54.897344, "lon": 9.8221818}, {"type": "node", "id": 4582326065, "lat": 54.8971481, "lon": 9.8218814}, {"type": "node", "id": 4582326066, "lat": 54.89699, "lon": 9.8214415}, {"type": "node", "id": 4582326067, "lat": 54.896916, "lon": 9.8207602}, {"type": "node", "id": 4582326068, "lat": 54.8969499, "lon": 9.8196713}, {"type": "node", "id": 4582326069, "lat": 54.8971041, "lon": 9.8186204}, {"type": "node", "id": 4582326070, "lat": 54.8977072, "lon": 9.816061}, {"type": "node", "id": 4582326071, "lat": 54.904576, "lon": 9.8238805}, {"type": "node", "id": 4582326072, "lat": 54.9047796, "lon": 9.8236231}, {"type": "node", "id": 4582326073, "lat": 54.906317, "lon": 9.8233334}, {"type": "node", "id": 4582326074, "lat": 54.9069816, "lon": 9.8237169}, {"type": "node", "id": 4582326075, "lat": 54.9101974, "lon": 9.8252163}, {"type": "node", "id": 4582326076, "lat": 54.908236, "lon": 9.8241568}, {"type": "node", "id": 4582326077, "lat": 54.9161075, "lon": 9.8295231}, {"type": "node", "id": 4582326078, "lat": 54.9124783, "lon": 9.8267551}, {"type": "node", "id": 4582326079, "lat": 54.9221665, "lon": 9.8329921}, {"type": "node", "id": 4744906328, "lat": 54.9153091, "lon": 9.8197902}, {"type": "node", "id": 4744906370, "lat": 54.9134155, "lon": 9.8204668}, {"type": "node", "id": 4744906420, "lat": 54.9153133, "lon": 9.819336}, {"type": "node", "id": 4744906477, "lat": 54.9151556, "lon": 9.8215572}, {"type": "node", "id": 4744908968, "lat": 54.9046112, "lon": 9.8243055}, {"type": "node", "id": 4845272401, "lat": 54.8973208, "lon": 9.8034833}, {"type": "node", "id": 4845272402, "lat": 54.8988084, "lon": 9.8038146}, {"type": "node", "id": 4845272403, "lat": 54.8989596, "lon": 9.8036697}, {"type": "node", "id": 4845272404, "lat": 54.899467, "lon": 9.8028302}, {"type": "node", "id": 5177816418, "lat": 54.9134302, "lon": 9.7831836}, {"type": "node", "id": 5207883763, "lat": 54.9112766, "lon": 9.7850619}, {"type": "node", "id": 5267743265, "lat": 54.9237279, "lon": 9.8011914}, {"type": "node", "id": 5267743287, "lat": 54.9225086, "lon": 9.7853959}, {"type": "node", "id": 5267743288, "lat": 54.9232146, "lon": 9.8020443}, {"type": "node", "id": 5267743289, "lat": 54.9236308, "lon": 9.8019236}, {"type": "node", "id": 5267743290, "lat": 54.9236153, "lon": 9.8013523}, {"type": "node", "id": 5345205772, "lat": 54.8982725, "lon": 9.8035168}, {"type": "node", "id": 5345205773, "lat": 54.8974168, "lon": 9.803604}, {"type": "node", "id": 5411773306, "lat": 54.8971196, "lon": 9.8036523}, {"type": "node", "id": 5411773307, "lat": 54.897172, "lon": 9.8036885}, {"type": "node", "id": 5411773308, "lat": 54.8970085, "lon": 9.8034927}, {"type": "node", "id": 5411773309, "lat": 54.8955926, "lon": 9.8062178}, {"type": "node", "id": 5411773310, "lat": 54.8949802, "lon": 9.8083636}, {"type": "node", "id": 5411773328, "lat": 54.8964671, "lon": 9.8133539}, {"type": "node", "id": 5424297678, "lat": 54.9231264, "lon": 9.8305721}, {"type": "node", "id": 5424297679, "lat": 54.9230951, "lon": 9.83087}, {"type": "node", "id": 5424307533, "lat": 54.918647, "lon": 9.8239433}, {"type": "node", "id": 5424307545, "lat": 54.9186811, "lon": 9.8241095}, {"type": "node", "id": 6707552849, "lat": 54.9135897, "lon": 9.7830507}, {"type": "node", "id": 6707552850, "lat": 54.9156082, "lon": 9.781642}, {"type": "node", "id": 6707564136, "lat": 54.914894, "lon": 9.7820389}, {"type": "node", "id": 6707564138, "lat": 54.9141435, "lon": 9.7826314}, {"type": "node", "id": 7593169197, "lat": 54.9025484, "lon": 9.8248349}, {"type": "node", "id": 7593169202, "lat": 54.8974273, "lon": 9.8188484}, {"type": "node", "id": 7593169203, "lat": 54.8973879, "lon": 9.8191005}, {"type": "node", "id": 7593169204, "lat": 54.8970478, "lon": 9.8189194}, {"type": "node", "id": 8527549247, "lat": 54.9156018, "lon": 9.7816621}, {"type": "node", "id": 9136951986, "lat": 54.93224, "lon": 9.8090905}, {"type": "node", "id": 9136951987, "lat": 54.9313462, "lon": 9.8089188}, {"type": "node", "id": 9136951988, "lat": 54.9304831, "lon": 9.8094553}, {"type": "node", "id": 9136951989, "lat": 54.9313123, "lon": 9.8098281}, {"type": "node", "id": 9136951990, "lat": 54.9298312, "lon": 9.8093292}, {"type": "node", "id": 9136951991, "lat": 54.9301996, "lon": 9.8086023}, {"type": "node", "id": 9136951992, "lat": 54.9299145, "lon": 9.8097879}, {"type": "node", "id": 9136951993, "lat": 54.9322199, "lon": 9.8115581}, {"type": "node", "id": 9136962554, "lat": 54.9321044, "lon": 9.8142886}, {"type": "node", "id": 9136962555, "lat": 54.9323633, "lon": 9.8141652}, {"type": "node", "id": 9136962556, "lat": 54.931864, "lon": 9.8159033}, {"type": "node", "id": 9136962557, "lat": 54.932052, "lon": 9.8169494}, {"type": "node", "id": 9136962558, "lat": 54.9316821, "lon": 9.8193553}, {"type": "node", "id": 9136962559, "lat": 54.9314772, "lon": 9.819712}, {"type": "node", "id": 9136962560, "lat": 54.931434, "lon": 9.8201546}, {"type": "node", "id": 9136962561, "lat": 54.9315403, "lon": 9.8207206}, {"type": "node", "id": 9136962562, "lat": 54.9321198, "lon": 9.8195833}, {"type": "node", "id": 9136962563, "lat": 54.9321556, "lon": 9.8192044}, {"type": "node", "id": 9136962564, "lat": 54.9316513, "lon": 9.8211658}, {"type": "node", "id": 9979850180, "lat": 54.9054966, "lon": 9.8234567}, {"type": "node", "id": 10764671271, "lat": 54.9167686, "lon": 9.7786513}, {"type": "node", "id": 11053566912, "lat": 54.8955208, "lon": 9.8157412}, {"type": "node", "id": 11053566929, "lat": 54.895692, "lon": 9.8060161}, {"type": "node", "id": 11053566930, "lat": 54.8957255, "lon": 9.805948}, {"type": "node", "id": 11166319869, "lat": 54.9120928, "lon": 9.7845273}, {"type": "node", "id": 12118503277, "lat": 54.916782, "lon": 9.830118}, {"type": "node", "id": 12118532886, "lat": 54.9144003, "lon": 9.8256556}, {"type": "node", "id": 12752325705, "lat": 54.907588, "lon": 9.7859846}, {"type": "node", "id": 12752325706, "lat": 54.9073883, "lon": 9.7861469}, {"type": "node", "id": 12752325707, "lat": 54.9072264, "lon": 9.786281}, {"type": "node", "id": 12752325708, "lat": 54.9069018, "lon": 9.7862609}, {"type": "node", "id": 12752325709, "lat": 54.9068247, "lon": 9.7861791}, {"type": "node", "id": 12752325710, "lat": 54.9065764, "lon": 9.7860074}, {"type": "node", "id": 12752325711, "lat": 54.906305, "lon": 9.7859108}, {"type": "node", "id": 12752325712, "lat": 54.9058779, "lon": 9.7859216}, {"type": "node", "id": 12752325713, "lat": 54.9055679, "lon": 9.7859725}, {"type": "node", "id": 12752325714, "lat": 54.9053782, "lon": 9.7861361}, {"type": "node", "id": 12752325715, "lat": 54.9052641, "lon": 9.7863695}, {"type": "node", "id": 12752325716, "lat": 54.9047475, "lon": 9.7877267}, {"type": "node", "id": 12752325717, "lat": 54.9042741, "lon": 9.7886226}, {"type": "way", "id": 261658950, "nodes": [1503903705, 12752325705, 12752325706, 12752325707, 12752325708, 12752325709, 12752325710, 12752325711, 12752325712, 12752325713, 12752325714, 12752325715, 12752325716, 12752325717, 273496463, 256451917, 257934609, 404456560, 404456556, 404456565, 276805097, 276805096, 277194515, 1444782750, 1444782747, 1444782746, 2425024840, 2425024841, 2425024848, 2425024869, 1445236122, 1444782769, 1444782758, 1444782756, 256451918, 4845272404, 4845272403, 4845272402, 2482546960, 5345205772, 5345205773, 4845272401, 5411773307, 5411773306, 5411773308, 265606997, 11053566930, 11053566929, 5411773309, 256451922, 5411773310, 256451898, 1403182048, 1403182055, 1403182049, 1403182056, 5411773328, 1403182053, 1403182047, 1403182050, 1403182045, 1403182054, 1403182052, 256451899, 11053566912, 1403182046, 1403182051, 256454705, 256035076, 4582326070, 4582326069, 7593169202, 7593169203, 7593169204, 4582326068, 4582326067, 4582326066, 4582326065, 4582326064, 4582326063, 4582326062, 4582326061, 4582326060, 4582326059, 4582326058, 4582326057, 4582326056, 4582326055, 4582326054, 1905360290, 274345472, 4582326053, 4582326052, 7593169197, 4582326051, 4582326050, 4582326049, 4582326048, 4582326044, 4582326045, 4582326046, 4582326047, 4744908968, 4582326071, 4582326072, 9979850180, 4582326043, 4582326073, 4582326074, 4582326076, 4582326075, 272803819, 4582326078, 4582326041, 4582326042, 4582326026, 4582326025, 4582326024, 4582326027, 4582326028, 4744906370, 4582326029, 4582326030, 4582326023, 4582326022, 4582326021, 4744906420, 4582326020, 4744906328, 4744906477, 4582326019, 4582326031, 4582326032, 4582326033, 4582326034, 4582326035, 4582326036, 12118532886, 4582326037, 4582326038, 4582326039, 4582326040, 272803820, 4582326077, 12118503277, 272803821, 256454707, 272803822, 256451905, 4582326079, 272803823, 5424297679, 5424297678, 3138120194, 4582325784, 4582325785, 4582325786, 4582325787, 3098817501, 4582325890, 4582325889, 4582325788, 3098817511, 3098817472, 3098817523, 3098817538, 3098817574, 3098817468, 3098817463, 2091032618, 2091032556, 256451906, 267255312, 2434261097, 267255313, 256451907, 2527175660, 9136962564, 9136962561, 9136962560, 9136962559, 9136962558, 9136962562, 9136962563, 269429683, 256451908, 9136962557, 9136962556, 9136962554, 9136962555, 2381790353, 256451909, 9136951993, 9136951986, 9136951987, 9136951989, 9136951988, 9136951991, 9136951990, 9136951992, 269429615, 4377022448, 4377022447, 4377022449, 4377022450, 4377022446, 4377022445, 269562594, 269562595, 4377812097, 4377811881, 269429616, 257950063, 4377811853, 257950064, 269561273, 269561274, 257950065, 275362528, 269561275, 280836130, 269561276, 269562082, 269562083, 3887612399, 388341503, 2381789948, 269561277, 2381789930, 269562146, 5424307545, 5424307533, 271880493, 272809341, 272809342, 269561278, 269562344, 1914283146, 1914283149, 1914283151, 1914283159, 269561279, 269563659, 1914283182, 269562084, 269561280, 4456183896, 4456183895, 4456183901, 4456183915, 257950067, 269561281, 5267743288, 269559188, 257950069, 257950070, 259817079, 257950071, 257950072, 5267743287, 257950073, 257950074, 4491328929, 257949722, 4491328930, 2835727955, 2835727924, 2835727919, 2835727918, 2835727917, 4491328928, 256451912, 2835727914, 2835727913, 2835727912, 2835727911, 2835727910, 4491328927, 4491328926, 2835727909, 2835727908, 2835727905, 4491328931, 256451913, 2228740422, 3556971520, 2985121740, 2985121738, 21934734, 10764671271, 21934735, 21934736, 3556970984, 6707552850, 8527549247, 21934737, 21934738, 2986159056, 6707564136, 2122433047, 6707564138, 2122433048, 6707552849, 5177816418, 21934749, 21934750, 11166319869, 5207883763, 256451915, 3898278430, 2228740433, 3898278428, 262655606, 1308214440, 256451916, 21934755, 1503903654, 1665776783, 1503903688, 1503903712, 1503903705], "tags": {"landuse": "residential"}}, {"type": "way", "id": 544991824, "nodes": [5267743289, 257950068, 269559183, 292676977, 269559184, 269559185, 269559186, 269559187, 5267743265, 5267743290, 5267743289], "tags": {"landuse": "residential"}}]}